destruction/FakeFloat.py
destruction/FakeMath.py
destruction/__init__.py
destruction-0.1.3.dist-info/DESCRIPTION.rst
destruction-0.1.3.dist-info/METADATA
destruction-0.1.3.dist-info/RECORD
destruction-0.1.3.dist-info/WHEEL
destruction-0.1.3.dist-info/metadata.json
destruction-0.1.3.dist-info/top_level.txt
